redashsync/__init__.py
redashsync/main.py
redashsync/config/__init__.py
redashsync/config/yaml.py
redashsync/redash/__init__.py
redashsync/redash/data.py
redashsync/slack/__init__.py
redashsync/slack/messages.py
redashsync-0.0.8.dist-info/METADATA
redashsync-0.0.8.dist-info/WHEEL
redashsync-0.0.8.dist-info/top_level.txt
redashsync-0.0.8.dist-info/RECORD
