Metadata-Version: 2.1
Name: redashsync
Version: 0.0.8
Summary: A tool integrating Redash with Slack
Home-page: UNKNOWN
Author: Yun
Author-email: ysjhmtb@gmail.com
License: UNKNOWN
Keywords: Redash,Slack
Platform: UNKNOWN
Classifier: Programming Language :: Python :: 3.11
Requires-Python: >=3.11
Requires-Dist: PyYAML
Requires-Dist: requests
Requires-Dist: seaborn
Requires-Dist: slack-sdk
Requires-Dist: cron-converter
